pycaverdock/__init__.py
pycaverdock/caverdock.py
pycaverdock/cfggen.py
pycaverdock/direction.py
pycaverdock/energy_profile.py
pycaverdock/experiment.py
pycaverdock/mgltoolswrapper.py
pycaverdock/plotting.py
pycaverdock/screening.py
pycaverdock/trajectory_type.py
pycaverdock/tunnel.py
pycaverdock/utils.py
pycaverdock/bin/__init__.py
pycaverdock/bin/analyseeprofile.py
pycaverdock/bin/analysis.py
pycaverdock/bin/energyprofile.py
pycaverdock/bin/extendtunnel.py
pycaverdock/bin/prepareconf.py
pycaverdock/bin/reverseeprofile.py
pycaverdock-1.2.0.dist-info/LICENSE
pycaverdock-1.2.0.dist-info/METADATA
pycaverdock-1.2.0.dist-info/WHEEL
pycaverdock-1.2.0.dist-info/entry_points.txt
pycaverdock-1.2.0.dist-info/top_level.txt
pycaverdock-1.2.0.dist-info/RECORD
