Metadata-Version: 2.1
Name: pycaverdock
Version: 1.2.0
Summary: Python API for CaverDock
Home-page: https://loschmidt.chemi.muni.cz/caverdock
Author: CaverDock team
Author-email: caver@caver.cz
Keywords: CaverDock,protein,tunnel,docking,ligand
Classifier: Development Status :: 5 - Production/Stable
Classifier: Environment :: Console
Classifier: Intended Audience :: Science/Research
Classifier: License :: OSI Approved :: MIT License
Classifier: Programming Language :: Python :: 3 :: Only
Classifier: Operating System :: POSIX
Classifier: Topic :: Scientific/Engineering :: Bio-Informatics
Requires-Python: >=3.6
License-File: LICENSE
Requires-Dist: click (>=7)
Requires-Dist: discretizer (>=1.1.0)
Requires-Dist: pandas (>=1)
Requires-Dist: seaborn (>=0.9)
Requires-Dist: matplotlib (>=3)
Requires-Dist: pyyaml (>=5)
Requires-Dist: tqdm (>=4.28)
Requires-Dist: pylru (>=1.2.0)
Requires-Dist: dataclasses (>=0.8) ; python_version < "3.7"
